itk_smoothingrecursiveyvvgaussianfilter-0.0.1.dist-info/WHEEL
itk_smoothingrecursiveyvvgaussianfilter-0.0.1.dist-info/LICENSE
itk_smoothingrecursiveyvvgaussianfilter-0.0.1.dist-info/RECORD
itk_smoothingrecursiveyvvgaussianfilter-0.0.1.dist-info/top_level.txt
itk_smoothingrecursiveyvvgaussianfilter-0.0.1.dist-info/METADATA
itk/SmoothingRecursiveYvvGaussianFilterPython.py
itk/itkSmoothingRecursiveYvvGaussianImageFilterPython.py
itk/_SmoothingRecursiveYvvGaussianFilterPython.so
itk/Configuration/SmoothingRecursiveYvvGaussianFilterConfig.py
